{
  "date": "June 2014",
  "number": "2.714",
  "years": [
    {
      "date": "2002",
      "value": "2.617",
      "year": "2002"
    },
    {
      "date": "2003",
      "value": "2.638",
      "year": "2003"
    },
    {
      "date": "2004",
      "value": "2.651",
      "year": "2004"
    },
    {
      "date": "2005",
      "value": "2.589",
      "year": "2005"
    },
    {
      "date": "2006",
      "value": "2.641",
      "year": "2006"
    },
    {
      "date": "2007",
      "value": "2.772",
      "year": "2007"
    },
    {
      "date": "2008",
      "value": "2.65",
      "year": "2008"
    },
    {
      "date": "2009",
      "value": "2.556",
      "year": "2009"
    },
    {
      "date": "2010",
      "value": "2.626",
      "year": "2010"
    },
    {
      "date": "2011",
      "value": "2.593",
      "year": "2011"
    },
    {
      "date": "2012",
      "value": "2.754",
      "year": "2012"
    },
    {
      "date": "2013",
      "value": "2.714",
      "year": "2013"
    }
  ],
  "quarters": [],
  "months": [],
  "sourceDatasets": [],
  "cdid": "RAID120",
  "unit": "m",
  "preUnit": "",
  "source": "Office for National Statistics",
  "notes": [
    "Methods changes mid-2008 and mid 2011"
  ],
  "relatedDocuments": [
    {
      "title": "Internal Migration, England and Wales, Year Ending June 2013",
      "summary": "Summarised statistics on residential moves between local authorities and regions in England and Wales and the UK.",
      "uri": "/peoplepopulationandcommunity/populationandmigration/migrationwithintheuk/bulletins/internalmigrationenglandandwalesyearendingjune2013"
    }
  ],
  "nationalStatistic": true,
  "type": "timeseries",
  "title": "Residents moving between local authorities",
  "uri": "/peoplepopulationandcommunity/populationandmigration/migrationwithintheuk/timeseries/raid120",
  "breadcrumb": [
    {
      "title": "Home",
      "summary": "The UK\u0027s largest independent producer of official statistics and the recognised national statistical institute of the UK.",
      "uri": "/"
    },
    {
      "title": "People, population and community",
      "summary": "Statistics in this area tell us a lot about the people living in the UK. From the level and growth in the population, to data and analysis on how households spend their money. We also have data on crime, divorce, diseases and religion here as well as much more. These statistics have a wide range of users and uses and they help us build a detailed picture of the country we live in. ",
      "uri": "/peoplepopulationandcommunity"
    },
    {
      "title": "Population and migration",
      "summary": "Population and migration statistics describe the size, age, sex structure and geographic distribution of the UK population. They also consider changes to the UK population and the factors driving these changes. These statistics have a wide range of uses; they are used by central government, local government and the health sector for planning, resource allocation and managing the economy. Additionally, they are used by a wide range of people such as market researchers, academics and those in special interest groups.",
      "uri": "/peoplepopulationandcommunity/populationandmigration"
    },
    {
      "title": "Migration within the UK",
      "summary": "Internal migration refers to residential moves between different geographic areas within the UK. These statistics are compiled from data from main three sources: The NHS Patient Register, The NHS Central Register (NHSCR) and the Higher Education Statistics Agency (HESA). ",
      "uri": "/peoplepopulationandcommunity/populationandmigration/migrationwithintheuk"
    }
  ]
}