{
  "sections": [
    {
      "uri": "/businessindustryandtrade/retailindustry",
      "index": 0
    },
    {
      "uri": "/businessindustryandtrade/internationaltrade",
      "index": 1
    },
    {
      "uri": "/businessindustryandtrade/manufacturingandproductionindustry",
      "index": 2
    },
    {
      "uri": "/businessindustryandtrade/constructionindustry",
      "index": 3
    },
    {
      "uri": "/businessindustryandtrade/businessactivitysizeandlocation",
      "index": 4
    },
    {
      "uri": "/businessindustryandtrade/changestobusiness",
      "index": 5
    },
    {
      "uri": "/businessindustryandtrade/itandinternetindustry",
      "index": 6
    },
    {
      "uri": "/businessindustryandtrade/tourismindustry",
      "index": 7
    }
  ],
  "index": 0,
  "type": "taxonomy_landing_page",
  "uri": "/businessindustryandtrade",
  "breadcrumb": [
    {
      "uri": "/"
    }
  ],
  "description": {
    "title": "Business, industry and trade",
    "summary": "Statistics in this area are related to the production and trade of good and services. These statistics are important for users looking to learn more about this section of the UK economy. Key statistics here are figures on retail sales, business activity, indices for the construction and manufacturing industries and international trade."
  }
}